memfs/__init__.py
memfs/_version.py
memfs/api.py
memfs/cli.py
memfs/cli_with_shell.py
memfs/memfs.py
memfs-0.1.8.dist-info/licenses/LICENSE
memfs-0.1.8.dist-info/METADATA
memfs-0.1.8.dist-info/WHEEL
memfs-0.1.8.dist-info/entry_points.txt
memfs-0.1.8.dist-info/top_level.txt
memfs-0.1.8.dist-info/RECORD
