Metadata-Version: 2.4
Name: memfs
Version: 0.1.8
Summary: Generate grpc API Service based on function
Home-page: https://github.com/pyfunc/memfs
Author: Tom Sapletta
Author-email: info@softreck.dev
License: Apache-2.0
Classifier: Development Status :: 3 - Alpha
Classifier: Environment :: Console
Classifier: Intended Audience :: Developers
Classifier: License :: OSI Approved :: Apache Software License
Classifier: Operating System :: OS Independent
Classifier: Programming Language :: Python :: 3
Classifier: Programming Language :: Python :: 3.11
Classifier: Programming Language :: Python :: 3.12
Classifier: Programming Language :: Python :: 3.13
Classifier: Topic :: Software Development :: Libraries :: Python Modules
Requires-Python: >=3.11
License-File: LICENSE
Requires-Dist: grpcio==1.59.3
Requires-Dist: grpcio-tools==1.59.3
Requires-Dist: protobuf==4.25.1
Requires-Dist: jinja2==3.1.2
Requires-Dist: weasyprint==60.1
Dynamic: license-file
